Metadata-Version: 2.1
Name: opigallus
Version: 0.9.2
Summary: opigallus
Author: Gallus
Author-email: bkmz_repvby@mail.ru
